AngularDispersion.py
PlanckPolarization.py
PlotPolarizationAngles.py
StructureFunctionAnalysis.py
Utilities.py
__init__.py
PolarSi-1.0.0.dist-info/LICENSE
PolarSi-1.0.0.dist-info/METADATA
PolarSi-1.0.0.dist-info/WHEEL
PolarSi-1.0.0.dist-info/top_level.txt
PolarSi-1.0.0.dist-info/RECORD
